film_central/__init__.py
film_central/vadapav/__init__.py
film_central/vadapav/scraper.py
film_central/vidsrcme/__init__.py
film_central/vidsrcme/scraper.py
film_central/vidsrcto/__init__.py
film_central/vidsrcto/scraper.py
film_central/vidsrcto/ext/__init__.py
film_central/vidsrcto/ext/vidplay.py
mov_cli_films/__init__.py
mov_cli_films-1.3.13.dist-info/LICENSE
mov_cli_films-1.3.13.dist-info/METADATA
mov_cli_films-1.3.13.dist-info/WHEEL
mov_cli_films-1.3.13.dist-info/top_level.txt
mov_cli_films-1.3.13.dist-info/RECORD
